LICENSE
MANIFEST.in
README.rst
setup.py
sftmpl/__init__.py
sftmpl.egg-info/PKG-INFO
sftmpl.egg-info/SOURCES.txt
sftmpl.egg-info/dependency_links.txt
sftmpl.egg-info/entry_points.txt
sftmpl.egg-info/top_level.txt