Metadata-Version: 1.1
Name: sftmpl
Version: 0.1
Summary: Single file templater
Home-page: http://github.com/pdebuyl/sftmpl
Author: Pierre de Buyl <pdebuyl at sign pdebuyl.be>
Author-email: pdebuyl at sign pdebuyl dot be
License: BSD
Platform: UNKNOWN
Classifier: Development Status :: 4 - Beta
Classifier: Environment :: Console
Classifier: Intended Audience :: Science/Research
Classifier: License :: OSI Approved :: BSD License
Classifier: Operating System :: OS Independent
Classifier: Programming Language :: Python :: 2.7
Classifier: Programming Language :: Python :: 3
Classifier: Topic :: Utilities
